nostr_dvm/__init__.py
nostr_dvm/bot.py
nostr_dvm/dvm.py
nostr_dvm/framework.py
nostr_dvm/subscription.py
nostr_dvm/backends/__init__.py
nostr_dvm/backends/discover/__init__.py
nostr_dvm/backends/discover/utils.py
nostr_dvm/backends/discover/modules/__init__.py
nostr_dvm/backends/discover/modules/image_interrogator/__init__.py
nostr_dvm/backends/discover/modules/image_interrogator/image_interrogator.py
nostr_dvm/backends/discover/modules/image_interrogator/version.py
nostr_dvm/backends/discover/modules/image_upscale/__init__.py
nostr_dvm/backends/discover/modules/image_upscale/image_upscale_realesrgan.py
nostr_dvm/backends/discover/modules/image_upscale/inference_realesrgan.py
nostr_dvm/backends/discover/modules/image_upscale/version.py
nostr_dvm/backends/discover/modules/stablediffusionxl/__init__.py
nostr_dvm/backends/discover/modules/stablediffusionxl/lora.py
nostr_dvm/backends/discover/modules/stablediffusionxl/stablediffusionxl-img2img.py
nostr_dvm/backends/discover/modules/stablediffusionxl/stablediffusionxl.py
nostr_dvm/backends/discover/modules/stablediffusionxl/version.py
nostr_dvm/backends/discover/modules/whisperx/__init__.py
nostr_dvm/backends/discover/modules/whisperx/version.py
nostr_dvm/backends/discover/modules/whisperx/whisperx_transcript.py
nostr_dvm/backends/mlx/__init__.py
nostr_dvm/backends/mlx/modules/__init__.py
nostr_dvm/backends/mlx/modules/stable_diffusion/__init__.py
nostr_dvm/backends/mlx/modules/stable_diffusion/clip.py
nostr_dvm/backends/mlx/modules/stable_diffusion/config.py
nostr_dvm/backends/mlx/modules/stable_diffusion/model_io.py
nostr_dvm/backends/mlx/modules/stable_diffusion/sampler.py
nostr_dvm/backends/mlx/modules/stable_diffusion/tokenizer.py
nostr_dvm/backends/mlx/modules/stable_diffusion/unet.py
nostr_dvm/backends/mlx/modules/stable_diffusion/vae.py
nostr_dvm/interfaces/__init__.py
nostr_dvm/interfaces/dvmtaskinterface.py
nostr_dvm/tasks/__init__.py
nostr_dvm/tasks/advanced_search.py
nostr_dvm/tasks/advanced_search_wine.py
nostr_dvm-1.1.3.dist-info/licenses/LICENSE
nostr_dvm-1.1.3.dist-info/METADATA
nostr_dvm-1.1.3.dist-info/WHEEL
nostr_dvm-1.1.3.dist-info/top_level.txt
nostr_dvm-1.1.3.dist-info/RECORD
